sisedeinversiones/__init__.py
sisedeinversiones/main.py
sisedeinversiones/form_eight/__init__.py
sisedeinversiones/form_eight/eight.py
sisedeinversiones/lista_ejecucion/__init__.py
sisedeinversiones/lista_ejecucion/lista_ejecucion_simple.py
sisedeinversiones/ssi/__init__.py
sisedeinversiones/ssi/main_ssi.py
sisedeinversiones/utils/__init__.py
sisedeinversiones/utils/read_utils.py
tests/__init__.py
tests/test_form_eight.py
tests/test_lista_ejecucion.py
tests/test_ssi.py
SiSedeInversiones-1.0.0.dist-info/LICENSE
SiSedeInversiones-1.0.0.dist-info/METADATA
SiSedeInversiones-1.0.0.dist-info/WHEEL
SiSedeInversiones-1.0.0.dist-info/top_level.txt
SiSedeInversiones-1.0.0.dist-info/RECORD
