Metadata-Version: 2.1
Name: SiSedeInversiones
Version: 1.0.0
Summary: This package is dedicated to automating the extraction of data found in the Peruvian state's Investment Monitoring System - SSI portal, where public investment projects in Peru can be monitored through Unique Investment Codes (CUI).
Home-page: https://github.com/JelsinPalomino/SiSedeInversiones
Author: Jelsin Stalin Palomino Huaytapuma
Author-email: jstpalomino@hotmail.com
License: MIT
Keywords: web-scraping,Peru,rpa,SSI,Inversiones
Classifier: Programming Language :: Python
Classifier: Operating System :: Microsoft :: Windows :: Windows 10
Classifier: Intended Audience :: Education
License-File: LICENSE
Requires-Dist: pandas
Requires-Dist: rpa
Requires-Dist: openpyxl
